{
    "file": ".\\all_drive\\red_drive_2235.jpg",
    "image_size": [
        {
            "width": 1920,
            "height": 1080,
            "depth": 3
        }
    ],
    "categories": [
        {
            "class_id": 1,
            "name": "red4"
        },
        {
            "class_id": 1,
            "name": "red4"
        }
    ],
    "annotations": [
        {
            "class_id": 1,
            "left": 505,
            "top": 434,
            "width": 250,
            "height": 233
        },
        {
            "class_id": 1,
            "left": 970,
            "top": 434,
            "width": 96,
            "height": 172
        }
    ]
}